linux_touchpad/__init__.py
linux_touchpad/__main__.py
linux_touchpad/linux-touchpad.lock
linux_touchpad/main.py
linux_touchpad/touchpad.py
linux_touchpad/watchdog.py
linux_touchpad-0.2.5.dist-info/LICENSE
linux_touchpad-0.2.5.dist-info/WHEEL
linux_touchpad-0.2.5.dist-info/METADATA
linux_touchpad-0.2.5.dist-info/RECORD
