Metadata-Version: 2.1
Name: linux-touchpad
Version: 0.2.5
Summary: Auto-disable laptop touchpad when a mouse is detected.
Home-page: https://github.com/Zer0897/linux-touchpad
License: MIT
Keywords: linux,touchpad,auto,disable,mouse
Author: Noah
Author-email: noah@coronasoftware.net
Requires-Python: >=3.6
Classifier: License :: OSI Approved :: MIT License
Classifier: Programming Language :: Python :: 3
Classifier: Programming Language :: Python :: 3.6
Classifier: Programming Language :: Python :: 3.7
Requires-Dist: filelock (>=3.0,<4.0)
Requires-Dist: pyudev (>=0.21.0,<0.22.0)
Project-URL: Repository, https://github.com/Zer0897/linux-touchpad
